README.md
setup.py
groot/__init__.py
groot/adversary.py
groot/attack.py
groot/datasets.py
groot/model.py
groot/toolbox.py
groot/treant.py
groot/util.py
groot/visualization.py
groot/provably_robust_boosting/__init__.py
groot/provably_robust_boosting/classifiers.py
groot/provably_robust_boosting/data.py
groot/provably_robust_boosting/robust_boosting.py
groot/provably_robust_boosting/stump_ensemble.py
groot/provably_robust_boosting/tree_ensemble.py
groot/provably_robust_boosting/utils.py
groot/provably_robust_boosting/wrapper.py
groot/verification/__init__.py
groot/verification/decision_tree_attack.py
groot/verification/kantchelian_attack.py
groot_trees.egg-info/PKG-INFO
groot_trees.egg-info/SOURCES.txt
groot_trees.egg-info/dependency_links.txt
groot_trees.egg-info/requires.txt
groot_trees.egg-info/top_level.txt