Metadata-Version: 2.1
Name: groot-trees
Version: 0.0.15
Summary: Growing Robust Decision Trees
Home-page: https://github.com/tudelft-cda-lab/GROOT
Author: Daniel Vos
Author-email: D.A.Vos@tudelft.nl
License: UNKNOWN
Platform: UNKNOWN
Classifier: Programming Language :: Python :: 3
Classifier: License :: OSI Approved :: MIT License
Classifier: Operating System :: OS Independent
Requires-Python: >=3.6
